{
  "generated_at": "2026-02-22T19:55:09",
  "n_trials": 8,
  "best_trial": {
    "trial": 3,
    "gamma": 0.001,
    "k": 1400,
    "r": 0.00015,
    "neighbor_mode": "4",
    "min_dense_points": null,
    "trajectories": 76,
    "original_points": 2305,
    "feature_points": 587,
    "compression_rate_dr": 0.7453362255965292,
    "distance_similarity_dl": 0.955263506293357,
    "ld_score": 1.7005997318898862,
    "cluster_coverage": 1.0,
    "n_clusters": 380,
    "largest_cluster_points": 32,
    "largest_cluster_share": 0.054514480408858604,
    "nodes": 21,
    "edges": 40,
    "transitions": 84,
    "score": 1.1377864864938394,
    "runtime_sec": 0.25114760000724345,
    "rss_mb": 285.58984375,
    "trial_dir": "f:\\PyTorch_GPU\\ISLs\\CEE-International_shipping_lanes_\\Region_wise_netwoks\\region_4\\NLSN_Extraction\\results\\gamma_0p001",
    "feature_points_csv": "f:\\PyTorch_GPU\\ISLs\\CEE-International_shipping_lanes_\\Region_wise_netwoks\\region_4\\NLSN_Extraction\\results\\gamma_0p001\\feature_points.csv",
    "map_html": "f:\\PyTorch_GPU\\ISLs\\CEE-International_shipping_lanes_\\Region_wise_netwoks\\region_4\\NLSN_Extraction\\results\\gamma_0p001\\nlsn_map.html"
  },
  "all_trials": [
    {
      "trial": 1,
      "gamma": 0.0001,
      "k": 1400,
      "r": 0.00015,
      "neighbor_mode": "4",
      "min_dense_points": null,
      "trajectories": 76,
      "original_points": 2305,
      "feature_points": 781,
      "compression_rate_dr": 0.6611713665943602,
      "distance_similarity_dl": 0.9717105402595106,
      "ld_score": 1.632881906853871,
      "cluster_coverage": 1.0,
      "n_clusters": 463,
      "largest_cluster_points": 40,
      "largest_cluster_share": 0.05121638924455826,
      "nodes": 30,
      "edges": 50,
      "transitions": 104,
      "score": 1.0997237243615392,
      "runtime_sec": 2.3486776999779977,
      "rss_mb": 285.23828125,
      "trial_dir": "f:\\PyTorch_GPU\\ISLs\\CEE-International_shipping_lanes_\\Region_wise_netwoks\\region_4\\NLSN_Extraction\\results\\gamma_0p0001",
      "feature_points_csv": "f:\\PyTorch_GPU\\ISLs\\CEE-International_shipping_lanes_\\Region_wise_netwoks\\region_4\\NLSN_Extraction\\results\\gamma_0p0001\\feature_points.csv",
      "map_html": "f:\\PyTorch_GPU\\ISLs\\CEE-International_shipping_lanes_\\Region_wise_netwoks\\region_4\\NLSN_Extraction\\results\\gamma_0p0001\\nlsn_map.html",
      "generated_at": "2026-02-22T19:55:07",
      "plsn_params": {
        "k": 1400,
        "r": 0.00015,
        "neighbor_mode": "4",
        "min_dense_points": null
      }
    },
    {
      "trial": 2,
      "gamma": 0.0005,
      "k": 1400,
      "r": 0.00015,
      "neighbor_mode": "4",
      "min_dense_points": null,
      "trajectories": 76,
      "original_points": 2305,
      "feature_points": 640,
      "compression_rate_dr": 0.7223427331887202,
      "distance_similarity_dl": 0.9573807412014987,
      "ld_score": 1.679723474390219,
      "cluster_coverage": 1.0,
      "n_clusters": 404,
      "largest_cluster_points": 36,
      "largest_cluster_share": 0.05625,
      "nodes": 22,
      "edges": 38,
      "transitions": 80,
      "score": 1.1267604995123301,
      "runtime_sec": 0.2803247999981977,
      "rss_mb": 285.50390625,
      "trial_dir": "f:\\PyTorch_GPU\\ISLs\\CEE-International_shipping_lanes_\\Region_wise_netwoks\\region_4\\NLSN_Extraction\\results\\gamma_0p0005",
      "feature_points_csv": "f:\\PyTorch_GPU\\ISLs\\CEE-International_shipping_lanes_\\Region_wise_netwoks\\region_4\\NLSN_Extraction\\results\\gamma_0p0005\\feature_points.csv",
      "map_html": "f:\\PyTorch_GPU\\ISLs\\CEE-International_shipping_lanes_\\Region_wise_netwoks\\region_4\\NLSN_Extraction\\results\\gamma_0p0005\\nlsn_map.html",
      "generated_at": "2026-02-22T19:55:07",
      "plsn_params": {
        "k": 1400,
        "r": 0.00015,
        "neighbor_mode": "4",
        "min_dense_points": null
      }
    },
    {
      "trial": 3,
      "gamma": 0.001,
      "k": 1400,
      "r": 0.00015,
      "neighbor_mode": "4",
      "min_dense_points": null,
      "trajectories": 76,
      "original_points": 2305,
      "feature_points": 587,
      "compression_rate_dr": 0.7453362255965292,
      "distance_similarity_dl": 0.955263506293357,
      "ld_score": 1.7005997318898862,
      "cluster_coverage": 1.0,
      "n_clusters": 380,
      "largest_cluster_points": 32,
      "largest_cluster_share": 0.054514480408858604,
      "nodes": 21,
      "edges": 40,
      "transitions": 84,
      "score": 1.1377864864938394,
      "runtime_sec": 0.25114760000724345,
      "rss_mb": 285.58984375,
      "trial_dir": "f:\\PyTorch_GPU\\ISLs\\CEE-International_shipping_lanes_\\Region_wise_netwoks\\region_4\\NLSN_Extraction\\results\\gamma_0p001",
      "feature_points_csv": "f:\\PyTorch_GPU\\ISLs\\CEE-International_shipping_lanes_\\Region_wise_netwoks\\region_4\\NLSN_Extraction\\results\\gamma_0p001\\feature_points.csv",
      "map_html": "f:\\PyTorch_GPU\\ISLs\\CEE-International_shipping_lanes_\\Region_wise_netwoks\\region_4\\NLSN_Extraction\\results\\gamma_0p001\\nlsn_map.html",
      "generated_at": "2026-02-22T19:55:08",
      "plsn_params": {
        "k": 1400,
        "r": 0.00015,
        "neighbor_mode": "4",
        "min_dense_points": null
      }
    },
    {
      "trial": 4,
      "gamma": 0.002,
      "k": 1400,
      "r": 0.00015,
      "neighbor_mode": "4",
      "min_dense_points": null,
      "trajectories": 76,
      "original_points": 2305,
      "feature_points": 520,
      "compression_rate_dr": 0.7744034707158352,
      "distance_similarity_dl": 0.9169548690118045,
      "ld_score": 1.6913583397276395,
      "cluster_coverage": 1.0,
      "n_clusters": 356,
      "largest_cluster_points": 28,
      "largest_cluster_share": 0.05384615384615385,
      "nodes": 17,
      "edges": 25,
      "transitions": 53,
      "score": 1.1341838044568884,
      "runtime_sec": 0.23142520000692457,
      "rss_mb": 285.60546875,
      "trial_dir": "f:\\PyTorch_GPU\\ISLs\\CEE-International_shipping_lanes_\\Region_wise_netwoks\\region_4\\NLSN_Extraction\\results\\gamma_0p002",
      "feature_points_csv": "f:\\PyTorch_GPU\\ISLs\\CEE-International_shipping_lanes_\\Region_wise_netwoks\\region_4\\NLSN_Extraction\\results\\gamma_0p002\\feature_points.csv",
      "map_html": "f:\\PyTorch_GPU\\ISLs\\CEE-International_shipping_lanes_\\Region_wise_netwoks\\region_4\\NLSN_Extraction\\results\\gamma_0p002\\nlsn_map.html",
      "generated_at": "2026-02-22T19:55:08",
      "plsn_params": {
        "k": 1400,
        "r": 0.00015,
        "neighbor_mode": "4",
        "min_dense_points": null
      }
    },
    {
      "trial": 5,
      "gamma": 0.005,
      "k": 1400,
      "r": 0.00015,
      "neighbor_mode": "4",
      "min_dense_points": null,
      "trajectories": 76,
      "original_points": 2305,
      "feature_points": 433,
      "compression_rate_dr": 0.8121475054229935,
      "distance_similarity_dl": 0.8999134885582524,
      "ld_score": 1.712060993981246,
      "cluster_coverage": 1.0,
      "n_clusters": 308,
      "largest_cluster_points": 23,
      "largest_cluster_share": 0.053117782909930716,
      "nodes": 14,
      "edges": 15,
      "transitions": 25,
      "score": 1.1312916623864349,
      "runtime_sec": 0.24125859997002408,
      "rss_mb": 285.61328125,
      "trial_dir": "f:\\PyTorch_GPU\\ISLs\\CEE-International_shipping_lanes_\\Region_wise_netwoks\\region_4\\NLSN_Extraction\\results\\gamma_0p005",
      "feature_points_csv": "f:\\PyTorch_GPU\\ISLs\\CEE-International_shipping_lanes_\\Region_wise_netwoks\\region_4\\NLSN_Extraction\\results\\gamma_0p005\\feature_points.csv",
      "map_html": "f:\\PyTorch_GPU\\ISLs\\CEE-International_shipping_lanes_\\Region_wise_netwoks\\region_4\\NLSN_Extraction\\results\\gamma_0p005\\nlsn_map.html",
      "generated_at": "2026-02-22T19:55:08",
      "plsn_params": {
        "k": 1400,
        "r": 0.00015,
        "neighbor_mode": "4",
        "min_dense_points": null
      }
    },
    {
      "trial": 6,
      "gamma": 0.01,
      "k": 1400,
      "r": 0.00015,
      "neighbor_mode": "4",
      "min_dense_points": null,
      "trajectories": 76,
      "original_points": 2305,
      "feature_points": 372,
      "compression_rate_dr": 0.8386117136659437,
      "distance_similarity_dl": 0.8302593838606511,
      "ld_score": 1.6688710975265948,
      "cluster_coverage": 1.0,
      "n_clusters": 265,
      "largest_cluster_points": 21,
      "largest_cluster_share": 0.056451612903225805,
      "nodes": 13,
      "edges": 9,
      "transitions": 19,
      "score": 1.1121841641136438,
      "runtime_sec": 0.21515169995836914,
      "rss_mb": 285.6171875,
      "trial_dir": "f:\\PyTorch_GPU\\ISLs\\CEE-International_shipping_lanes_\\Region_wise_netwoks\\region_4\\NLSN_Extraction\\results\\gamma_0p01",
      "feature_points_csv": "f:\\PyTorch_GPU\\ISLs\\CEE-International_shipping_lanes_\\Region_wise_netwoks\\region_4\\NLSN_Extraction\\results\\gamma_0p01\\feature_points.csv",
      "map_html": "f:\\PyTorch_GPU\\ISLs\\CEE-International_shipping_lanes_\\Region_wise_netwoks\\region_4\\NLSN_Extraction\\results\\gamma_0p01\\nlsn_map.html",
      "generated_at": "2026-02-22T19:55:09",
      "plsn_params": {
        "k": 1400,
        "r": 0.00015,
        "neighbor_mode": "4",
        "min_dense_points": null
      }
    },
    {
      "trial": 7,
      "gamma": 0.02,
      "k": 1400,
      "r": 0.00015,
      "neighbor_mode": "4",
      "min_dense_points": null,
      "trajectories": 76,
      "original_points": 2305,
      "feature_points": 311,
      "compression_rate_dr": 0.8650759219088937,
      "distance_similarity_dl": 0.7523187845768913,
      "ld_score": 1.617394706485785,
      "cluster_coverage": 1.0,
      "n_clusters": 215,
      "largest_cluster_points": 18,
      "largest_cluster_share": 0.05787781350482315,
      "nodes": 13,
      "edges": 8,
      "transitions": 16,
      "score": 1.0879930533690079,
      "runtime_sec": 0.20674479997251183,
      "rss_mb": 285.6171875,
      "trial_dir": "f:\\PyTorch_GPU\\ISLs\\CEE-International_shipping_lanes_\\Region_wise_netwoks\\region_4\\NLSN_Extraction\\results\\gamma_0p02",
      "feature_points_csv": "f:\\PyTorch_GPU\\ISLs\\CEE-International_shipping_lanes_\\Region_wise_netwoks\\region_4\\NLSN_Extraction\\results\\gamma_0p02\\feature_points.csv",
      "map_html": "f:\\PyTorch_GPU\\ISLs\\CEE-International_shipping_lanes_\\Region_wise_netwoks\\region_4\\NLSN_Extraction\\results\\gamma_0p02\\nlsn_map.html",
      "generated_at": "2026-02-22T19:55:09",
      "plsn_params": {
        "k": 1400,
        "r": 0.00015,
        "neighbor_mode": "4",
        "min_dense_points": null
      }
    },
    {
      "trial": 8,
      "gamma": 0.05,
      "k": 1400,
      "r": 0.00015,
      "neighbor_mode": "4",
      "min_dense_points": null,
      "trajectories": 76,
      "original_points": 2305,
      "feature_points": 248,
      "compression_rate_dr": 0.8924078091106291,
      "distance_similarity_dl": 0.6305438415457233,
      "ld_score": 1.5229516506563523,
      "cluster_coverage": 1.0,
      "n_clusters": 167,
      "largest_cluster_points": 17,
      "largest_cluster_share": 0.06854838709677419,
      "nodes": 8,
      "edges": 1,
      "transitions": 1,
      "score": 1.0004265396946843,
      "runtime_sec": 0.16491009999299422,
      "rss_mb": 285.75390625,
      "trial_dir": "f:\\PyTorch_GPU\\ISLs\\CEE-International_shipping_lanes_\\Region_wise_netwoks\\region_4\\NLSN_Extraction\\results\\gamma_0p05",
      "feature_points_csv": "f:\\PyTorch_GPU\\ISLs\\CEE-International_shipping_lanes_\\Region_wise_netwoks\\region_4\\NLSN_Extraction\\results\\gamma_0p05\\feature_points.csv",
      "map_html": "f:\\PyTorch_GPU\\ISLs\\CEE-International_shipping_lanes_\\Region_wise_netwoks\\region_4\\NLSN_Extraction\\results\\gamma_0p05\\nlsn_map.html",
      "generated_at": "2026-02-22T19:55:09",
      "plsn_params": {
        "k": 1400,
        "r": 0.00015,
        "neighbor_mode": "4",
        "min_dense_points": null
      }
    }
  ],
  "results_csv": "f:\\PyTorch_GPU\\ISLs\\CEE-International_shipping_lanes_\\Region_wise_netwoks\\region_4\\NLSN_Extraction\\results\\nlsn_gamma_sweep_results.csv"
}